[{
    "navn": "Hovedindgang",
    "beskrivelse": "Her går man ind i bygningen",
    "billede": "hovedindgang",
    "position": {
        "lat": 55.706369,
        "lng": 12.539088
    },
    "id": "hovedindgang"

}, {
    "navn": "Fredagsbar",
    "beskrivelse": "Moonbar, dakke dak ja tak",
    "billede": "fredagsbar",
    "position": {
        "lat": 55.706479,
        "lng": 12.539270
    },
    "id": "fredagsbar"

}, {
    "navn": "Kantinen",
    "beskrivelse": "Et lækkert sted, hvor man kan købe mad og drikke",
    "billede": "kantine",
    "position": {
        "lat": 55.706206,
        "lng": 12.539531
    },
    "id": "kantine"

}, {
    "navn": "Et meget mystisk område",
    "beskrivelse": "Ved ikke helt",
    "billede": "mystisksted",
    "position": {
        "lat": 55.706257,
        "lng": 12.540199
    },
    "id": "?"

}]
